topsis_abhayjeet/__init__.py
topsis_abhayjeet/topsis.py
topsis_abhayjeet-1.1.2.dist-info/METADATA
topsis_abhayjeet-1.1.2.dist-info/WHEEL
topsis_abhayjeet-1.1.2.dist-info/entry_points.txt
topsis_abhayjeet-1.1.2.dist-info/top_level.txt
topsis_abhayjeet-1.1.2.dist-info/RECORD
