Metadata-Version: 2.4
Name: topsis-abhayjeet
Version: 1.1.2
Summary: Implementation of TOPSIS (Technique for Order Preference by Similarity to Ideal Solution)
Home-page: https://pypi.org/project/topsis-abhayjeet/
Author: Abhayjeet
Author-email: abhayjeet5465@gmail.com
Classifier: Programming Language :: Python :: 3
Classifier: License :: OSI Approved :: MIT License
Classifier: Operating System :: OS Independent
Requires-Python: >=3.7
Requires-Dist: pandas
Requires-Dist: numpy
Dynamic: author
Dynamic: author-email
Dynamic: classifier
Dynamic: description
Dynamic: description-content-type
Dynamic: home-page
Dynamic: requires-dist
Dynamic: requires-python
Dynamic: summary
